mcmc.cpython-313-x86_64-linux-gnu.so
neemuds_mcmc/LICENSE.md
neemuds_mcmc/mcmc.so
neemuds_mcmc-2.43.6.dist-info/licenses/LICENSE.md
neemuds_mcmc-2.43.6.dist-info/METADATA
neemuds_mcmc-2.43.6.dist-info/WHEEL
neemuds_mcmc-2.43.6.dist-info/top_level.txt
neemuds_mcmc-2.43.6.dist-info/RECORD
