Metadata-Version: 2.4
Name: neemuds_mcmc
Version: 2.43.6
Summary: Python wrapper library sub-project of Neemuds for inversion based on Markov chain Monte Carlo method
Home-page: 
License: 3-clause BSD 2.0
Classifier: License :: OSI Approved :: BSD License
Classifier: Programming Language :: Python :: 3
License-File: LICENSE.md
Dynamic: classifier
Dynamic: description
Dynamic: license
Dynamic: license-file
Dynamic: summary
